Serializer/DeserializerJSON.py
Serializer/DeserializerXML.py
Serializer/ParserJSON.py
Serializer/ParserXML.py
Serializer/SerializerFactory.py
Serializer/SerializerJSON.py
Serializer/SerializerXML.py
Serializer/__init__.py
Serializer/constants.py
Serializer_CuteHedgehog-0.0.1.dist-info/METADATA
Serializer_CuteHedgehog-0.0.1.dist-info/WHEEL
Serializer_CuteHedgehog-0.0.1.dist-info/top_level.txt
Serializer_CuteHedgehog-0.0.1.dist-info/RECORD
